HafrenHaver/__init__.py
HafrenHaver/a.py
HafrenHaver/aggregator.py
HafrenHaver/angle_app.py
HafrenHaver/angled_circle.py
HafrenHaver/app.py
HafrenHaver/artwork.py
HafrenHaver/artwork_client.py
HafrenHaver/artwork_server.py
HafrenHaver/atp.py
HafrenHaver/audio_gui.py
HafrenHaver/av.py
HafrenHaver/bar_cadence.py
HafrenHaver/bjorklund_old.py
HafrenHaver/brain_waves.py
HafrenHaver/buf.py
HafrenHaver/cache.py
HafrenHaver/cadence.py
HafrenHaver/chromatic.py
HafrenHaver/circle_app.py
HafrenHaver/circled_angle.py
HafrenHaver/circled_circle.py
HafrenHaver/circled_polygon.py
HafrenHaver/circled_square.py
HafrenHaver/client.py
HafrenHaver/composite_app.py
HafrenHaver/constants.py
HafrenHaver/counting.py
HafrenHaver/cropping_app.py
HafrenHaver/decorated_gui.py
HafrenHaver/draw.py
HafrenHaver/fractal_test_0.py
HafrenHaver/fractal_test_00.py
HafrenHaver/fractal_test_1.py
HafrenHaver/fractal_test_10.py
HafrenHaver/fractal_test_2.py
HafrenHaver/fractal_test_20.py
HafrenHaver/fractal_test_3.py
HafrenHaver/fractal_test_30.py
HafrenHaver/fractal_test_4.py
HafrenHaver/geom.py
HafrenHaver/geometry.py
HafrenHaver/gps.py
HafrenHaver/gps_app.py
HafrenHaver/gps_client.py
HafrenHaver/gps_server.py
HafrenHaver/gui.py
HafrenHaver/hal.py
HafrenHaver/hallang.py
HafrenHaver/hallib.py
HafrenHaver/hilbjork.py
HafrenHaver/isochronic.py
HafrenHaver/key.py
HafrenHaver/lc.py
HafrenHaver/magic_circle.py
HafrenHaver/main.py
HafrenHaver/map_app.py
HafrenHaver/mode.py
HafrenHaver/moon_app.py
HafrenHaver/network.py
HafrenHaver/neural_style_transfer.py
HafrenHaver/numerology.py
HafrenHaver/one_punch.py
HafrenHaver/orientation.py
HafrenHaver/pager.py
HafrenHaver/pattern.py
HafrenHaver/pexels_pager.py
HafrenHaver/pexels_results.py
HafrenHaver/phrase_cadence.py
HafrenHaver/pixabay_pager.py
HafrenHaver/pixabay_results.py
HafrenHaver/play.py
HafrenHaver/polygon_app.py
HafrenHaver/polygoned_circle.py
HafrenHaver/prefetcher.py
HafrenHaver/pygameplotlib.py
HafrenHaver/random_util.py
HafrenHaver-1.0.277.dist-info/LICENSE
HafrenHaver-1.0.277.dist-info/METADATA
HafrenHaver-1.0.277.dist-info/WHEEL
HafrenHaver-1.0.277.dist-info/top_level.txt
HafrenHaver-1.0.277.dist-info/RECORD
