Metadata-Version: 2.1
Name: HafrenHaver
Version: 1.0.277
Summary: Goes on and on about the River Severn
Home-page: https://InnovAnon-Inc.github.io/HafrenHaver
Author: Innovations Anonymous
Author-email: InnovAnon-Inc@protonmail.com
License: unlicense
Project-URL: Source, https://github.com/InnovAnon-Inc/HafrenHaver
Project-URL: Bug Reports, https://github.com/InnovAnon-Inc/HafrenHaver/issues
Project-URL: CIS, https://app.circleci.com/pipelines/github/InnovAnon-Inc/HafrenHaver
Project-URL: Funding, https://www.patreon.com/InnovAnon
Project-URL: Say Thanks!, https://saythanks.io/to/InnovAnon-Inc%40protonmail.com
Keywords: InnovAnon,Innovations,Anonymous,Hafren Haver
Platform: UNKNOWN
Classifier: Programming Language :: Python :: 3 :: Only
Classifier: Programming Language :: Python :: 3.9
Classifier: Programming Language :: Python :: Implementation :: CPython
Classifier: Programming Language :: Other
Classifier: Programming Language :: Unix Shell
Classifier: Operating System :: POSIX :: Linux
Classifier: Development Status :: 2 - Pre-Alpha
Classifier: License :: Public Domain
Classifier: License :: OSI Approved :: MIT License
Classifier: Topic :: Artistic Software
Classifier: Topic :: Education :: Computer Aided Instruction (CAI)
Classifier: Topic :: Multimedia :: Graphics
Classifier: Topic :: Multimedia :: Sound/Audio :: Sound Synthesis
Classifier: Topic :: Religion
Classifier: Topic :: Scientific/Engineering :: Human Machine Interfaces
Classifier: Topic :: Software Development :: Libraries :: pygame
Classifier: Intended Audience :: Education
Classifier: Intended Audience :: Religion
Classifier: Intended Audience :: Science/Research
Classifier: Framework :: Matplotlib
Classifier: Framework :: Pytest
Classifier: Framework :: Sphinx
Requires-Python: >=3.6
Requires-Dist: astor
Requires-Dist: datetime
Requires-Dist: geocoder
Requires-Dist: geopy
Requires-Dist: hilbertcurve
Requires-Dist: nltk
Requires-Dist: numpy
Requires-Dist: pathlib
Requires-Dist: podsixnet
Requires-Dist: pygame
Requires-Dist: requests
Requires-Dist: skyfield
Requires-Dist: tatsu
Requires-Dist: wave
Provides-Extra: dist
Requires-Dist: setuptools ; extra == 'dist'
Requires-Dist: wheel ; extra == 'dist'
Requires-Dist: twine ; extra == 'dist'
Provides-Extra: site
Requires-Dist: sphinx ; extra == 'site'
Requires-Dist: sphinx-theme ; extra == 'site'
Provides-Extra: test
Requires-Dist: pytest ; extra == 'test'
Requires-Dist: pytest-html ; extra == 'test'
Requires-Dist: pytest-xdist ; extra == 'test'
